regexai/__init__.py
regexai/pattern.py
regexai-0.0.13.dist-info/Licence.txt
regexai-0.0.13.dist-info/METADATA
regexai-0.0.13.dist-info/WHEEL
regexai-0.0.13.dist-info/top_level.txt
regexai-0.0.13.dist-info/RECORD
