Metadata-Version: 2.1
Name: regexai
Version: 0.0.13
Summary: Tranform regex into regexai
Author: Shreyash Rote and Ritesh Tambe
Author-email: shreyashrote321@gmail.com
Keywords: openai,regex,pattern,text_analysis,text_preprocessing
Classifier: Development Status :: 1 - Planning
Classifier: Intended Audience :: Developers
Classifier: Programming Language :: Python :: 3
Classifier: Operating System :: Unix
Classifier: Operating System :: MacOS :: MacOS X
Classifier: Operating System :: Microsoft :: Windows
License-File: Licence.txt
Requires-Dist: openai
Requires-Dist: spacy
